MANIFEST.in
README.rst
britney_utils.py
requirements.txt
setup.py
britney_utils.egg-info/PKG-INFO
britney_utils.egg-info/SOURCES.txt
britney_utils.egg-info/dependency_links.txt
britney_utils.egg-info/top_level.txt