Metadata-Version: 1.1
Name: britney-utils
Version: 0.1.2
Summary: Utilities for the Python SPORE client called Britney
Home-page: https://github.com/unistra/britney-utils
Author: Arnaud Grausem
Author-email: arnaud.grausem@gmail.com
License: PSF
Download-URL: http://pypi.python.org/pypi/britney-utils
Keywords: SPORE,REST Api,client,britney
Platform: UNKNOWN
Classifier: Development Status :: 3 - Alpha
Classifier: Environment :: Web Environment
Classifier: Intended Audience :: Developers
Classifier: License :: OSI Approved :: BSD License
Classifier: Operating System :: OS Independent
Classifier: Programming Language :: Python :: 2.7
Classifier: Programming Language :: Python :: 3
